LICENSE
README.md
rangy/__init__.py
rangy/__version__.py
rangy/builtins.py
rangy/const.py
rangy/converters.py
rangy/distribute.py
rangy/exceptions.py
rangy/parse.py
rangy/rangy.py
rangy/registry.py
rangy-1.0.1.dist-info/LICENSE
rangy-1.0.1.dist-info/METADATA
rangy-1.0.1.dist-info/WHEEL
rangy-1.0.1.dist-info/RECORD
