Metadata-Version: 2.1
Name: rangy
Version: 1.0.1
Summary: Work with integer ranges with ease
Author: Arthur Debert
Author-email: arthur@debert.xyz
Requires-Python: >=3.9
Classifier: Programming Language :: Python :: 3
Classifier: Programming Language :: Python :: 3.9
Classifier: Programming Language :: Python :: 3.10
Classifier: Programming Language :: Python :: 3.11
Classifier: Programming Language :: Python :: 3.12
Classifier: Programming Language :: Python :: 3.13
